SomeGames/MatchingPennies.py
SomeGames/__init__.py
SomeGames/hangman.py
SomeGames/main.py
SomeGames/mnk.py
SomeGames-0.0.1.dist-info/METADATA
SomeGames-0.0.1.dist-info/WHEEL
SomeGames-0.0.1.dist-info/entry_points.txt
SomeGames-0.0.1.dist-info/top_level.txt
SomeGames-0.0.1.dist-info/RECORD
